leanapi/__init__.py
leanapi/config.py
leanapi/path.py
leanapi/router.py
leanapi/server.py
leanapi-0.0.12.dist-info/METADATA
leanapi-0.0.12.dist-info/WHEEL
leanapi-0.0.12.dist-info/top_level.txt
leanapi-0.0.12.dist-info/RECORD
