Metadata-Version: 2.1
Name: leanapi
Version: 0.0.12
Summary: Lean Api is a class layer for FastApi
Home-page: http://github.com/developerkitchentr/leanapi
Author: developerkitchen python team
Author-email: topluluk@developerkitchen.dev
License: MIT
Keywords: api,leanapi,fastapi
Classifier: Development Status :: 1 - Planning
Classifier: Topic :: Utilities
Classifier: License :: OSI Approved :: MIT License
Requires-Dist: fastapi (>=0.92.0)
Requires-Dist: uvicorn (>=0.13.4)
Requires-Dist: python-dotenv
Requires-Dist: pydantic (>=1.7.4)
